testghacookiecutter-0.0.100.dist-info/WHEEL
testghacookiecutter-0.0.100.dist-info/COPYING.md
testghacookiecutter-0.0.100.dist-info/RECORD
testghacookiecutter-0.0.100.dist-info/LICENSE.md
testghacookiecutter-0.0.100.dist-info/top_level.txt
testghacookiecutter-0.0.100.dist-info/METADATA
testghacookiecutter/_testghacookiecutter.cpython-39-i386-linux-gnu.so
testghacookiecutter/__init__.py
testghacookiecutter/include/test-gha-cookiecutter/test-gha-cookiecutter.hpp
testghacookiecutter/lib/cmake/test-gha-cookiecutter/test-gha-cookiecutter-config.cmake
