Metadata-Version: 2.1
Name: testghacookiecutter
Version: 0.0.100
Summary: Add short description here
Maintainer-email: Your Name <your@email.com>
License: MIT
Classifier: Programming Language :: Python :: 3
Classifier: Operating System :: OS Independent
Classifier: License :: OSI Approved :: MIT License
Requires-Python: >=3.8
License-File: LICENSE.md
License-File: COPYING.md
